tests/__init__.py
tests/test_mock_ar.py
tests/test_parse_ar.py
whoare/__init__.py
whoare/base.py
whoare/exceptions.py
whoare/news.py
whoare/serve.py
whoare/whoare.py
whoare/zone_parsers/__init__.py
whoare/zone_parsers/ar/__init__.py
whoare/zone_parsers/ar/news.py
whoare/zone_parsers/ar/news_from_blockchain.py
whoare/zone_parsers/ar/who.py
whoare-0.2.5.dist-info/licenses/LICENSE
whoare-0.2.5.dist-info/METADATA
whoare-0.2.5.dist-info/WHEEL
whoare-0.2.5.dist-info/entry_points.txt
whoare-0.2.5.dist-info/top_level.txt
whoare-0.2.5.dist-info/RECORD
